{"value":"{\"aid\": \"http://arxiv.org/abs/2504.04992v1\", \"title\": \"Error bound for the asymptotic expansion of the Hartman-Watson integral\", \"summary\": \"This note gives a bound on the error of the leading term of the $t\\\\to 0$\\nasymptotic expansion of the Hartman-Watson distribution $\\\\theta(r,t)$ in the\\nregime $rt=\\\\rho$ constant. The leading order term has the form\\n$\\\\theta(\\\\rho/t,t)=\\\\frac{1}{2\\\\pi t}e^{-\\\\frac{1}{t} (F(\\\\rho)-\\\\pi^2/2)} G(\\\\rho) (1\\n+ \\\\vartheta(t,\\\\rho))$, where the error term is bounded uniformly over $\\\\rho$ as\\n$|\\\\vartheta(t,\\\\rho)|\\\\leq \\\\frac{1}{70}t$.\", \"main_category\": \"math.CA\", \"categories\": \"math.CA,q-fin.CP\", \"published\": \"2025-04-07T12:18:19Z\"}"}
