{"value":"{\"aid\": \"http://arxiv.org/abs/2504.07897v1\", \"title\": \"The Constituent Quark Model\", \"summary\": \"In this chapter we give a pedagogical introduction to the constituent quark\\nmodel. The explanation of magnetic moments of the nucleons was crucial to\\nintroduce an effective quark mass for light quarks that nowadays are understood\\nas an effect of Spontaneous Chiral Symmetry Breaking in QCD. We give an\\noverview of the first applications of the model and an introduction to the most\\nmodern developments studying states beyond the naive quark model as tetraquarks\\nand pentaquarks.\", \"main_category\": \"hep-ph\", \"categories\": \"hep-ph,nucl-th\", \"published\": \"2025-04-10T16:14:37Z\"}"}
