{"value":"{\"aid\": \"http://arxiv.org/abs/2505.05012v1\", \"title\": \"Contact isotopies in the coherent-constructible correspondence\", \"summary\": \"The coherent-constructible correspondence is a realization of toric mirror\\nsymmetry in which the A-side is modeled by constructible sheaves on $T^n$. This\\npaper provides a geometric realization of the mirror Picard group action in\\nthis correspondence, characterizing it in terms of quantized contact isotopies\\nand providing a sheaf-theoretic counterpart to work of Hanlon in the\\nFukaya-Seidel setting. Given a toric Cartier divisor $D$, we consider a family\\nof homogeneous Hamiltonians $H_\\\\varepsilon$ on $T^* T^n$. Their flows act on\\nsheaves via a family of kernels $K_\\\\varepsilon$ on $T^n \\\\times T^n$. The nearby\\ncycles kernel $K_0$ corresponds heuristically to the Hamiltonian flow of the\\nnon-differentiable function $\\\\lim_{\\\\varepsilon \\\\to 0} H_\\\\varepsilon$, which is\\nthe pullback of the support function of $D$ along the cofiber projection. We\\nshow that the action of $K_0$ coincides with the convolution action of the\\nassociated twisted polytope sheaf, hence mirrors the action of $\\\\mathcal{O}(D)$\\non coherent sheaves.\", \"main_category\": \"math.AG\", \"categories\": \"math.AG,math.SG\", \"published\": \"2025-05-08T07:34:58Z\"}"}
