{"value":"{\"aid\": \"http://arxiv.org/abs/2505.05033v1\", \"title\": \"Waves in Bopp-Land{\\u00e9}-Thomas-Podolsky generalized electrodynamics\", \"summary\": \"We investigate the feasibility of probing Bopp-Land{\\\\'e}-Thomas-Podolsky\\ngeneralized electrodynamics with traveling and standing wave experiments. We\\nconsider wave propagation in vacuum and in a cold and non-magnetized plasma.\\nDispersion relations are found for all possible transverse and longitudinal\\nmodes. Longitudinal traveling waves are found which exhibit negative group\\nvelocities.\", \"main_category\": \"gr-qc\", \"categories\": \"gr-qc\", \"published\": \"2025-05-08T08:12:04Z\"}"}
